[
    {
        "Title": "EasyList ad servers third-party1",
        "Source": "https://filters.adtidy.org/extension/ublock/filters/122_optimized.txt",
        "Base Output Filename": "02-{FORMAT}.txt",
        "Header": {
            "Version": "2.0.96.73",
            "Title": "Fanboy's Annoyances (Optimized)"
        },
        "Conversion": [
            [
                "Total Lines Processed",
                20651
            ],
            [
                "Comment Lines",
                7
            ],
            [
                "Empty Lines",
                0
            ],
            [
                "Non-Domain-only Rules Excluded",
                20201
            ],
            [
                "Domain-only Rules Excluded (unsupported options)",
                41
            ],
            [
                "Domain-only Rules Excluded (exception conflict)",
                25
            ],
            [
                "Domain-only Rules Output",
                377
            ]
        ],
        "Output Formats": {
            "Just Domains": "02-justdomains.txt"
        },
        "Domains Output": 377
    },
    {
        "Title": "EasyList ad servers third-party2",
        "Source": "https://filters.adtidy.org/extension/ublock/filters/113_optimized.txt",
        "Base Output Filename": "03-{FORMAT}.txt",
        "Header": {
            "Version": "2.1.16.94",
            "Title": "Liste FR (Optimized)"
        },
        "Conversion": [
            [
                "Total Lines Processed",
                6113
            ],
            [
                "Comment Lines",
                7
            ],
            [
                "Empty Lines",
                0
            ],
            [
                "Non-Domain-only Rules Excluded",
                3612
            ],
            [
                "Domain-only Rules Excluded (unsupported options)",
                111
            ],
            [
                "Domain-only Rules Excluded (exception conflict)",
                0
            ],
            [
                "Domain-only Rules Output",
                2383
            ]
        ],
        "Output Formats": {
            "Just Domains": "03-justdomains.txt"
        },
        "Domains Output": 2383
    },
    {
        "Title": "EasyList ad servers third-party3",
        "Source": "https://filters.adtidy.org/extension/ublock/filters/6_optimized.txt",
        "Base Output Filename": "04-{FORMAT}.txt",
        "Header": {
            "Version": "2.0.30.44",
            "Title": "AdGuard German filter (Optimized)"
        },
        "Conversion": [
            [
                "Total Lines Processed",
                4119
            ],
            [
                "Comment Lines",
                251
            ],
            [
                "Empty Lines",
                0
            ],
            [
                "Non-Domain-only Rules Excluded",
                3673
            ],
            [
                "Domain-only Rules Excluded (unsupported options)",
                38
            ],
            [
                "Domain-only Rules Excluded (exception conflict)",
                51
            ],
            [
                "Domain-only Rules Output",
                106
            ]
        ],
        "Output Formats": {
            "Just Domains": "04-justdomains.txt"
        },
        "Domains Output": 106
    },
    {
        "Title": "EasyList ad servers third-party4",
        "Source": "https://filters.adtidy.org/extension/ublock/filters/101_optimized.txt",
        "Base Output Filename": "05-{FORMAT}.txt",
        "Header": {
            "Version": "2.0.95.74",
            "Title": "EasyList (Optimized)"
        },
        "Conversion": [
            [
                "Total Lines Processed",
                22017
            ],
            [
                "Comment Lines",
                7
            ],
            [
                "Empty Lines",
                0
            ],
            [
                "Non-Domain-only Rules Excluded",
                13013
            ],
            [
                "Domain-only Rules Excluded (unsupported options)",
                260
            ],
            [
                "Domain-only Rules Excluded (exception conflict)",
                43
            ],
            [
                "Domain-only Rules Output",
                8694
            ]
        ],
        "Output Formats": {
            "Just Domains": "05-justdomains.txt"
        },
        "Domains Output": 8694
    },
    {
        "Title": "EasyList ad servers third-party5",
        "Source": "https://filters.adtidy.org/extension/ublock/filters/4_optimized.txt",
        "Base Output Filename": "06-{FORMAT}.txt",
        "Header": {
            "Version": "2.0.71.77",
            "Title": "AdGuard Social Media filter (Optimized)"
        },
        "Conversion": [
            [
                "Total Lines Processed",
                7687
            ],
            [
                "Comment Lines",
                68
            ],
            [
                "Empty Lines",
                0
            ],
            [
                "Non-Domain-only Rules Excluded",
                7564
            ],
            [
                "Domain-only Rules Excluded (unsupported options)",
                3
            ],
            [
                "Domain-only Rules Excluded (exception conflict)",
                4
            ],
            [
                "Domain-only Rules Output",
                48
            ]
        ],
        "Output Formats": {
            "Just Domains": "06-justdomains.txt"
        },
        "Domains Output": 48
    },
    {
        "Title": "EasyList ad servers third-party6",
        "Source": "https://filters.adtidy.org/extension/ublock/filters/242_optimized.txt",
        "Base Output Filename": "07-{FORMAT}.txt",
        "Header": {
            "Version": "1.0.2.35",
            "Title": "NoCoin Filter List (Optimized)"
        },
        "Conversion": [
            [
                "Total Lines Processed",
                663
            ],
            [
                "Comment Lines",
                7
            ],
            [
                "Empty Lines",
                0
            ],
            [
                "Non-Domain-only Rules Excluded",
                215
            ],
            [
                "Domain-only Rules Excluded (unsupported options)",
                7
            ],
            [
                "Domain-only Rules Excluded (exception conflict)",
                0
            ],
            [
                "Domain-only Rules Output",
                434
            ]
        ],
        "Output Formats": {
            "Just Domains": "07-justdomains.txt"
        },
        "Domains Output": 434
    },
    {
        "Title": "EasyList ad servers third-party7",
        "Source": "https://filters.adtidy.org/extension/ublock/filters/210_optimized.txt",
        "Base Output Filename": "08-{FORMAT}.txt",
        "Header": {
            "Version": "2.0.2.44",
            "Title": "(Obsolete) Spam404 (Optimized)"
        },
        "Conversion": [
            [
                "Total Lines Processed",
                7264
            ],
            [
                "Comment Lines",
                7
            ],
            [
                "Empty Lines",
                0
            ],
            [
                "Non-Domain-only Rules Excluded",
                142
            ],
            [
                "Domain-only Rules Excluded (unsupported options)",
                0
            ],
            [
                "Domain-only Rules Excluded (exception conflict)",
                3
            ],
            [
                "Domain-only Rules Output",
                7112
            ]
        ],
        "Output Formats": {
            "Just Domains": "08-justdomains.txt"
        },
        "Domains Output": 7112
    },
    {
        "Title": "EasyList ad servers third-party8",
        "Source": "https://filters.adtidy.org/extension/ublock/filters/3_optimized.txt",
        "Base Output Filename": "09-{FORMAT}.txt",
        "Header": {
            "Version": "2.0.47.15",
            "Title": "AdGuard Tracking Protection filter (Optimized)"
        },
        "Conversion": [
            [
                "Total Lines Processed",
                34920
            ],
            [
                "Comment Lines",
                33
            ],
            [
                "Empty Lines",
                0
            ],
            [
                "Non-Domain-only Rules Excluded",
                5705
            ],
            [
                "Domain-only Rules Excluded (unsupported options)",
                66
            ],
            [
                "Domain-only Rules Excluded (exception conflict)",
                286
            ],
            [
                "Domain-only Rules Output",
                28830
            ]
        ],
        "Output Formats": {
            "Just Domains": "09-justdomains.txt"
        },
        "Domains Output": 28830
    },
    {
        "Title": "EasyList ad servers third-party9",
        "Source": "https://filters.adtidy.org/extension/ublock/filters/118_optimized.txt",
        "Base Output Filename": "10-{FORMAT}.txt",
        "Header": {
            "Version": "2.0.98.60",
            "Title": "EasyPrivacy (Optimized)"
        },
        "Conversion": [
            [
                "Total Lines Processed",
                14233
            ],
            [
                "Comment Lines",
                7
            ],
            [
                "Empty Lines",
                0
            ],
            [
                "Non-Domain-only Rules Excluded",
                4262
            ],
            [
                "Domain-only Rules Excluded (unsupported options)",
                104
            ],
            [
                "Domain-only Rules Excluded (exception conflict)",
                101
            ],
            [
                "Domain-only Rules Output",
                9759
            ]
        ],
        "Output Formats": {
            "Just Domains": "10-justdomains.txt"
        },
        "Domains Output": 9759
    },
    {
        "Title": "EasyList ad servers third-party10",
        "Source": "https://filters.adtidy.org/extension/ublock/filters/104_optimized.txt",
        "Base Output Filename": "11-{FORMAT}.txt",
        "Header": {
            "Version": "2.1.15.49",
            "Title": "EasyList China (Optimized)"
        },
        "Conversion": [
            [
                "Total Lines Processed",
                9699
            ],
            [
                "Comment Lines",
                72
            ],
            [
                "Empty Lines",
                0
            ],
            [
                "Non-Domain-only Rules Excluded",
                5452
            ],
            [
                "Domain-only Rules Excluded (unsupported options)",
                56
            ],
            [
                "Domain-only Rules Excluded (exception conflict)",
                10
            ],
            [
                "Domain-only Rules Output",
                4109
            ]
        ],
        "Output Formats": {
            "Just Domains": "11-justdomains.txt"
        },
        "Domains Output": 4109
    },
    {
        "Title": "EasyList ad servers third-party11",
        "Source": "https://filters.adtidy.org/extension/ublock/filters/2_optimized.txt",
        "Base Output Filename": "12-{FORMAT}.txt",
        "Header": {
            "Version": "2.2.54.9",
            "Title": "AdGuard Base filter + EasyList (Optimized)"
        },
        "Conversion": [
            [
                "Total Lines Processed",
                32775
            ],
            [
                "Comment Lines",
                1015
            ],
            [
                "Empty Lines",
                0
            ],
            [
                "Non-Domain-only Rules Excluded",
                22924
            ],
            [
                "Domain-only Rules Excluded (unsupported options)",
                339
            ],
            [
                "Domain-only Rules Excluded (exception conflict)",
                115
            ],
            [
                "Domain-only Rules Output",
                8382
            ]
        ],
        "Output Formats": {
            "Just Domains": "12-justdomains.txt"
        },
        "Domains Output": 8382
    },
    {
        "Title": "EasyList ad servers third-party12",
        "Source": "https://filters.adtidy.org/extension/ublock/filters/14_optimized.txt",
        "Base Output Filename": "13-{FORMAT}.txt",
        "Header": {
            "Version": "2.1.37.61",
            "Title": "AdGuard Annoyances filter (Optimized)"
        },
        "Conversion": [
            [
                "Total Lines Processed",
                18888
            ],
            [
                "Comment Lines",
                291
            ],
            [
                "Empty Lines",
                0
            ],
            [
                "Non-Domain-only Rules Excluded",
                17936
            ],
            [
                "Domain-only Rules Excluded (unsupported options)",
                67
            ],
            [
                "Domain-only Rules Excluded (exception conflict)",
                29
            ],
            [
                "Domain-only Rules Output",
                565
            ]
        ],
        "Output Formats": {
            "Just Domains": "13-justdomains.txt"
        },
        "Domains Output": 565
    },
    {
        "Title": "EasyList ad servers third-party13",
        "Source": "https://filters.adtidy.org/extension/ublock/filters/1_optimized.txt",
        "Base Output Filename": "14-{FORMAT}.txt",
        "Header": {
            "Version": "2.0.74.53",
            "Title": "AdGuard Russian filter (Optimized)"
        },
        "Conversion": [
            [
                "Total Lines Processed",
                9189
            ],
            [
                "Comment Lines",
                91
            ],
            [
                "Empty Lines",
                0
            ],
            [
                "Non-Domain-only Rules Excluded",
                7329
            ],
            [
                "Domain-only Rules Excluded (unsupported options)",
                63
            ],
            [
                "Domain-only Rules Excluded (exception conflict)",
                12
            ],
            [
                "Domain-only Rules Output",
                1694
            ]
        ],
        "Output Formats": {
            "Just Domains": "14-justdomains.txt"
        },
        "Domains Output": 1694
    },
    {
        "Title": "EasyList ad servers third-party14",
        "Source": "https://filters.adtidy.org/extension/ublock/filters/11_optimized.txt",
        "Base Output Filename": "15-{FORMAT}.txt",
        "Header": {
            "Version": "2.0.34.6",
            "Title": "AdGuard Mobile Ads filter (Optimized)"
        },
        "Conversion": [
            [
                "Total Lines Processed",
                5196
            ],
            [
                "Comment Lines",
                32
            ],
            [
                "Empty Lines",
                0
            ],
            [
                "Non-Domain-only Rules Excluded",
                4106
            ],
            [
                "Domain-only Rules Excluded (unsupported options)",
                25
            ],
            [
                "Domain-only Rules Excluded (exception conflict)",
                18
            ],
            [
                "Domain-only Rules Output",
                1015
            ]
        ],
        "Output Formats": {
            "Just Domains": "15-justdomains.txt"
        },
        "Domains Output": 1015
    },
    {
        "Title": "EasyList ad servers third-party15",
        "Source": "https://easylist-downloads.adblockplus.org/easylist.txt",
        "Base Output Filename": "16-{FORMAT}.txt",
        "Header": {
            "Version": "202210260425",
            "Last Modified": "26 Oct 2022 04:25 UTC",
            "License": "https://easylist.to/pages/licence.html",
            "Title": "EasyList",
            "Homepage": "https://easylist.to/"
        },
        "Conversion": [
            [
                "Total Lines Processed",
                55200
            ],
            [
                "Comment Lines",
                232
            ],
            [
                "Empty Lines",
                0
            ],
            [
                "Non-Domain-only Rules Excluded",
                29701
            ],
            [
                "Domain-only Rules Excluded (unsupported options)",
                2584
            ],
            [
                "Domain-only Rules Excluded (exception conflict)",
                63
            ],
            [
                "Domain-only Rules Output",
                22620
            ]
        ],
        "Output Formats": {
            "Just Domains": "16-justdomains.txt"
        },
        "Domains Output": 22620
    },
    {
        "Title": "EasyList ad servers third-party16",
        "Source": "https://easylist-downloads.adblockplus.org/easyprivacy.txt",
        "Base Output Filename": "17-{FORMAT}.txt",
        "Header": {
            "Version": "202210260425",
            "Last Modified": "26 Oct 2022 04:25 UTC",
            "License": "https://easylist.to/pages/licence.html",
            "Title": "EasyPrivacy",
            "Homepage": "https://easylist.to/"
        },
        "Conversion": [
            [
                "Total Lines Processed",
                31372
            ],
            [
                "Comment Lines",
                723
            ],
            [
                "Empty Lines",
                0
            ],
            [
                "Non-Domain-only Rules Excluded",
                9913
            ],
            [
                "Domain-only Rules Excluded (unsupported options)",
                230
            ],
            [
                "Domain-only Rules Excluded (exception conflict)",
                186
            ],
            [
                "Domain-only Rules Output",
                20320
            ]
        ],
        "Output Formats": {
            "Just Domains": "17-justdomains.txt"
        },
        "Domains Output": 20320
    },
    {
        "Title": "EasyList ad servers third-party17",
        "Source": "https://secure.fanboy.co.nz/fanboy-social.txt",
        "Base Output Filename": "18-{FORMAT}.txt",
        "Header": {
            "Version": "202210231440",
            "Last Modified": "2022-10-23 14:40 UTC",
            "License": "http://creativecommons.org/licenses/by/3.0/",
            "Title": "Fanboy's Social Blocking List",
            "Homepage": "https://easylist.to/"
        },
        "Conversion": [
            [
                "Total Lines Processed",
                20446
            ],
            [
                "Comment Lines",
                142
            ],
            [
                "Empty Lines",
                0
            ],
            [
                "Non-Domain-only Rules Excluded",
                20180
            ],
            [
                "Domain-only Rules Excluded (unsupported options)",
                10
            ],
            [
                "Domain-only Rules Excluded (exception conflict)",
                10
            ],
            [
                "Domain-only Rules Output",
                104
            ]
        ],
        "Output Formats": {
            "Just Domains": "18-justdomains.txt"
        },
        "Domains Output": 104
    },
    {
        "Title": "EasyList ad servers third-party18",
        "Source": "https://secure.fanboy.co.nz/fanboy-annoyance.txt",
        "Base Output Filename": "19-{FORMAT}.txt",
        "Header": {
            "Version": "202210200020",
            "Last Modified": "2022-10-20 00:20 UTC",
            "License": "http://creativecommons.org/licenses/by/3.0/",
            "Title": "Fanboy's Annoyance List",
            "Homepage": "https://easylist.to/"
        },
        "Conversion": [
            [
                "Total Lines Processed",
                57001
            ],
            [
                "Comment Lines",
                783
            ],
            [
                "Empty Lines",
                0
            ],
            [
                "Non-Domain-only Rules Excluded",
                55358
            ],
            [
                "Domain-only Rules Excluded (unsupported options)",
                59
            ],
            [
                "Domain-only Rules Excluded (exception conflict)",
                42
            ],
            [
                "Domain-only Rules Output",
                759
            ]
        ],
        "Output Formats": {
            "Just Domains": "19-justdomains.txt"
        },
        "Domains Output": 759
    },
    {
        "Title": "EasyList ad servers third-party19",
        "Source": "https://easylist-downloads.adblockplus.org/easylistgermany.txt",
        "Base Output Filename": "20-{FORMAT}.txt",
        "Header": {
            "Version": "202210260425",
            "Last Modified": "26 Oct 2022 04:25 UTC",
            "License": "https://easylist.github.io/pages/licence.html",
            "Title": "EasyList Germany",
            "Homepage": "https://easylist.github.io/"
        },
        "Conversion": [
            [
                "Total Lines Processed",
                4781
            ],
            [
                "Comment Lines",
                43
            ],
            [
                "Empty Lines",
                0
            ],
            [
                "Non-Domain-only Rules Excluded",
                4300
            ],
            [
                "Domain-only Rules Excluded (unsupported options)",
                77
            ],
            [
                "Domain-only Rules Excluded (exception conflict)",
                2
            ],
            [
                "Domain-only Rules Output",
                359
            ]
        ],
        "Output Formats": {
            "Just Domains": "20-justdomains.txt"
        },
        "Domains Output": 359
    },
    {
        "Title": "EasyList ad servers third-party20",
        "Source": "https://easylist-downloads.adblockplus.org/easylistitaly.txt",
        "Base Output Filename": "21-{FORMAT}.txt",
        "Header": {
            "Version": "202210260425",
            "Last Modified": "26 Oct 2022 04:25 UTC",
            "Title": "EasyList Italy",
            "Homepage": "https://easylist.to/"
        },
        "Conversion": [
            [
                "Total Lines Processed",
                9492
            ],
            [
                "Comment Lines",
                45
            ],
            [
                "Empty Lines",
                0
            ],
            [
                "Non-Domain-only Rules Excluded",
                9184
            ],
            [
                "Domain-only Rules Excluded (unsupported options)",
                68
            ],
            [
                "Domain-only Rules Excluded (exception conflict)",
                7
            ],
            [
                "Domain-only Rules Output",
                188
            ]
        ],
        "Output Formats": {
            "Just Domains": "21-justdomains.txt"
        },
        "Domains Output": 188
    },
    {
        "Title": "EasyList ad servers third-party21",
        "Source": "https://easylist-downloads.adblockplus.org/easylistdutch.txt",
        "Base Output Filename": "22-{FORMAT}.txt",
        "Header": {
            "Version": "202210260425",
            "Last Modified": "26 Oct 2022 04:25 UTC",
            "License": "https://easylist.to/pages/licence.html",
            "Title": "EasyList Dutch",
            "Homepage": "https://easylist.to/"
        },
        "Conversion": [
            [
                "Total Lines Processed",
                1128
            ],
            [
                "Comment Lines",
                46
            ],
            [
                "Empty Lines",
                0
            ],
            [
                "Non-Domain-only Rules Excluded",
                1041
            ],
            [
                "Domain-only Rules Excluded (unsupported options)",
                3
            ],
            [
                "Domain-only Rules Excluded (exception conflict)",
                2
            ],
            [
                "Domain-only Rules Output",
                36
            ]
        ],
        "Output Formats": {
            "Just Domains": "22-justdomains.txt"
        },
        "Domains Output": 36
    },
    {
        "Title": "EasyList ad servers third-party23",
        "Source": "https://easylist-downloads.adblockplus.org/easylistchina.txt",
        "Base Output Filename": "23-{FORMAT}.txt",
        "Header": {
            "Version": "202210260425",
            "Last Modified": "26 Oct 2022 04:25 UTC",
            "License": "https://easylist.to/pages/licence.html",
            "Title": "EasyList China",
            "Homepage": "https://github.com/easylist/easylistchina/"
        },
        "Conversion": [
            [
                "Total Lines Processed",
                22770
            ],
            [
                "Comment Lines",
                110
            ],
            [
                "Empty Lines",
                0
            ],
            [
                "Non-Domain-only Rules Excluded",
                13288
            ],
            [
                "Domain-only Rules Excluded (unsupported options)",
                196
            ],
            [
                "Domain-only Rules Excluded (exception conflict)",
                14
            ],
            [
                "Domain-only Rules Output",
                9162
            ]
        ],
        "Output Formats": {
            "Just Domains": "23-justdomains.txt"
        },
        "Domains Output": 9162
    },
    {
        "Title": "EasyList ad servers third-party24",
        "Source": "http://stanev.org/abp/adblock_bg.txt",
        "Base Output Filename": "24-{FORMAT}.txt",
        "Header": {
            "Title": "Bulgarian adblock list",
            "Homepage": "https://stanev.org/abp"
        },
        "Conversion": [
            [
                "Total Lines Processed",
                1104
            ],
            [
                "Comment Lines",
                17
            ],
            [
                "Empty Lines",
                1
            ],
            [
                "Non-Domain-only Rules Excluded",
                1083
            ],
            [
                "Domain-only Rules Excluded (unsupported options)",
                0
            ],
            [
                "Domain-only Rules Excluded (exception conflict)",
                0
            ],
            [
                "Domain-only Rules Output",
                4
            ]
        ],
        "Output Formats": {
            "Just Domains": "24-justdomains.txt"
        },
        "Domains Output": 4
    },
    {
        "Title": "EasyList ad servers third-party25",
        "Source": "https://raw.githubusercontent.com/heradhis/indonesianadblockrules/master/subscriptions/abpindo.txt",
        "Base Output Filename": "25-{FORMAT}.txt",
        "Header": {
            "Version": "202210251033",
            "Last Modified": "25 Oct 2022 10:33 UTC",
            "License": "https://raw.githubusercontent.com/ABPindo/indonesianadblockrules/master/LICENSE",
            "Title": "ABPindo",
            "Homepage": "https://github.com/ABPindo/indonesianadblockrules/"
        },
        "Conversion": [
            [
                "Total Lines Processed",
                8764
            ],
            [
                "Comment Lines",
                37
            ],
            [
                "Empty Lines",
                0
            ],
            [
                "Non-Domain-only Rules Excluded",
                8134
            ],
            [
                "Domain-only Rules Excluded (unsupported options)",
                148
            ],
            [
                "Domain-only Rules Excluded (exception conflict)",
                0
            ],
            [
                "Domain-only Rules Output",
                445
            ]
        ],
        "Output Formats": {
            "Just Domains": "25-justdomains.txt"
        },
        "Domains Output": 445
    },
    {
        "Title": "EasyList ad servers third-party26",
        "Source": "https://easylist-downloads.adblockplus.org/Liste_AR.txt",
        "Base Output Filename": "26-{FORMAT}.txt",
        "Header": {
            "Version": "202210260425",
            "Last Modified": "26 Oct 2022 04:25 UTC",
            "Title": "Liste AR",
            "Homepage": "https://code.google.com/p/liste-ar-adblock/"
        },
        "Conversion": [
            [
                "Total Lines Processed",
                2209
            ],
            [
                "Comment Lines",
                69
            ],
            [
                "Empty Lines",
                0
            ],
            [
                "Non-Domain-only Rules Excluded",
                1938
            ],
            [
                "Domain-only Rules Excluded (unsupported options)",
                133
            ],
            [
                "Domain-only Rules Excluded (exception conflict)",
                0
            ],
            [
                "Domain-only Rules Output",
                69
            ]
        ],
        "Output Formats": {
            "Just Domains": "26-justdomains.txt"
        },
        "Domains Output": 69
    },
    {
        "Title": "EasyList ad servers third-party27",
        "Source": "https://raw.githubusercontent.com/tomasko126/easylistczechandslovak/master/filters.txt",
        "Base Output Filename": "27-{FORMAT}.txt",
        "Header": {
            "License": "CC-BY-SA v4.0",
            "Title": "Easylist Czech and Slovak filter list",
            "Homepage": "http://adblock.sk"
        },
        "Conversion": [
            [
                "Total Lines Processed",
                552
            ],
            [
                "Comment Lines",
                53
            ],
            [
                "Empty Lines",
                0
            ],
            [
                "Non-Domain-only Rules Excluded",
                405
            ],
            [
                "Domain-only Rules Excluded (unsupported options)",
                2
            ],
            [
                "Domain-only Rules Excluded (exception conflict)",
                2
            ],
            [
                "Domain-only Rules Output",
                90
            ]
        ],
        "Output Formats": {
            "Just Domains": "27-justdomains.txt"
        },
        "Domains Output": 90
    },
    {
        "Title": "EasyList ad servers third-party28",
        "Source": "https://raw.githubusercontent.com/Latvian-List/adblock-latvian/master/lists/latvian-list.txt",
        "Base Output Filename": "28-{FORMAT}.txt",
        "Header": {
            "Version": "202208040804",
            "Last Modified": "2022-08-04 08:04 UTC",
            "License": "CC BY-SA 4.0  https://creativecommons.org/licenses/by-sa/4.0/",
            "Title": "Latvian List",
            "Homepage": "https://github.com/Latvian-List/adblock-latvian"
        },
        "Conversion": [
            [
                "Total Lines Processed",
                415
            ],
            [
                "Comment Lines",
                36
            ],
            [
                "Empty Lines",
                0
            ],
            [
                "Non-Domain-only Rules Excluded",
                336
            ],
            [
                "Domain-only Rules Excluded (unsupported options)",
                4
            ],
            [
                "Domain-only Rules Excluded (exception conflict)",
                2
            ],
            [
                "Domain-only Rules Output",
                37
            ]
        ],
        "Output Formats": {
            "Just Domains": "28-justdomains.txt"
        },
        "Domains Output": 37
    },
    {
        "Title": "EasyList ad servers third-party29",
        "Source": "https://raw.githubusercontent.com/easylist/EasyListHebrew/master/EasyListHebrew.txt",
        "Base Output Filename": "29-{FORMAT}.txt",
        "Header": {
            "Last Modified": "08 Oct 2022 22:50 UTC",
            "License": "https://easylist.to/pages/licence.html",
            "Title": "EasyList Hebrew",
            "Homepage": "https://github.com/easylist/EasyListHebrew"
        },
        "Conversion": [
            [
                "Total Lines Processed",
                1251
            ],
            [
                "Comment Lines",
                146
            ],
            [
                "Empty Lines",
                0
            ],
            [
                "Non-Domain-only Rules Excluded",
                741
            ],
            [
                "Domain-only Rules Excluded (unsupported options)",
                220
            ],
            [
                "Domain-only Rules Excluded (exception conflict)",
                1
            ],
            [
                "Domain-only Rules Output",
                143
            ]
        ],
        "Output Formats": {
            "Just Domains": "29-justdomains.txt"
        },
        "Domains Output": 143
    },
    {
        "Title": "EasyList ad servers third-party30",
        "Source": "https://raw.githubusercontent.com/EasyList-Lithuania/easylist_lithuania/master/easylistlithuania.txt",
        "Base Output Filename": "30-{FORMAT}.txt",
        "Header": {
            "Version": "19October2022v1",
            "Title": "EasyList Lithuania",
            "Homepage": "https://github.com/EasyList-Lithuania/easylist_lithuania"
        },
        "Conversion": [
            [
                "Total Lines Processed",
                1160
            ],
            [
                "Comment Lines",
                28
            ],
            [
                "Empty Lines",
                1
            ],
            [
                "Non-Domain-only Rules Excluded",
                1088
            ],
            [
                "Domain-only Rules Excluded (unsupported options)",
                13
            ],
            [
                "Domain-only Rules Excluded (exception conflict)",
                1
            ],
            [
                "Domain-only Rules Output",
                30
            ]
        ],
        "Output Formats": {
            "Just Domains": "30-justdomains.txt"
        },
        "Domains Output": 30
    },
    {
        "Title": "EasyList ad servers third-party31",
        "Source": "https://easylist-downloads.adblockplus.org/easyprivacy.tpl",
        "Base Output Filename": "31-{FORMAT}.txt",
        "Header": {},
        "Conversion": [
            [
                "Total Lines Processed",
                31368
            ],
            [
                "Comment Lines",
                0
            ],
            [
                "Empty Lines",
                0
            ],
            [
                "Non-Domain-only Rules Excluded",
                31368
            ],
            [
                "Domain-only Rules Excluded (unsupported options)",
                0
            ],
            [
                "Domain-only Rules Excluded (exception conflict)",
                0
            ],
            [
                "Domain-only Rules Output",
                0
            ]
        ],
        "Output Formats": {
            "Just Domains": "31-justdomains.txt"
        },
        "Domains Output": 0
    },
    {
        "Title": "EasyList ad servers third-party33",
        "Source": "https://raw.githubusercontent.com/AdguardTeam/FiltersRegistry/master/filters/filter_3_Spyware/filter.txt",
        "Base Output Filename": "33-{FORMAT}.txt",
        "Header": {
            "License": "https://github.com/AdguardTeam/AdguardFilters/blob/master/LICENSE",
            "Homepage": "https://github.com/AdguardTeam/AdGuardFilters"
        },
        "Conversion": [
            [
                "Total Lines Processed",
                41080
            ],
            [
                "Comment Lines",
                5467
            ],
            [
                "Empty Lines",
                13
            ],
            [
                "Non-Domain-only Rules Excluded",
                6286
            ],
            [
                "Domain-only Rules Excluded (unsupported options)",
                202
            ],
            [
                "Domain-only Rules Excluded (exception conflict)",
                316
            ],
            [
                "Domain-only Rules Output",
                28809
            ]
        ],
        "Output Formats": {
            "Just Domains": "33-justdomains.txt"
        },
        "Domains Output": 28809
    },
    {
        "Title": "EasyList ad servers third-party34",
        "Source": "https://raw.githubusercontent.com/AdguardTeam/FiltersRegistry/master/filters/filter_17_TrackParam/filter.txt",
        "Base Output Filename": "34-{FORMAT}.txt",
        "Header": {
            "License": "https://github.com/AdguardTeam/AdguardFilters/blob/master/LICENSE",
            "Homepage": "https://github.com/AdguardTeam/AdGuardFilters"
        },
        "Conversion": [
            [
                "Total Lines Processed",
                1168
            ],
            [
                "Comment Lines",
                369
            ],
            [
                "Empty Lines",
                3
            ],
            [
                "Non-Domain-only Rules Excluded",
                411
            ],
            [
                "Domain-only Rules Excluded (unsupported options)",
                388
            ],
            [
                "Domain-only Rules Excluded (exception conflict)",
                0
            ],
            [
                "Domain-only Rules Output",
                0
            ]
        ],
        "Output Formats": {
            "Just Domains": "34-justdomains.txt"
        },
        "Domains Output": 0
    },
    {
        "Title": "EasyList ad servers third-party35",
        "Source": "https://raw.githubusercontent.com/AdguardTeam/FiltersRegistry/master/filters/filter_4_Social/filter.txt",
        "Base Output Filename": "35-{FORMAT}.txt",
        "Header": {
            "License": "https://github.com/AdguardTeam/AdguardFilters/blob/master/LICENSE",
            "Homepage": "https://github.com/AdguardTeam/AdGuardFilters"
        },
        "Conversion": [
            [
                "Total Lines Processed",
                12910
            ],
            [
                "Comment Lines",
                777
            ],
            [
                "Empty Lines",
                8
            ],
            [
                "Non-Domain-only Rules Excluded",
                12074
            ],
            [
                "Domain-only Rules Excluded (unsupported options)",
                3
            ],
            [
                "Domain-only Rules Excluded (exception conflict)",
                4
            ],
            [
                "Domain-only Rules Output",
                52
            ]
        ],
        "Output Formats": {
            "Just Domains": "35-justdomains.txt"
        },
        "Domains Output": 52
    },
    {
        "Title": "EasyList ad servers third-party36",
        "Source": "https://raw.githubusercontent.com/AdguardTeam/FiltersRegistry/master/filters/filter_14_Annoyances/filter.txt",
        "Base Output Filename": "36-{FORMAT}.txt",
        "Header": {
            "License": "https://github.com/AdguardTeam/AdguardFilters/blob/master/LICENSE",
            "Homepage": "https://github.com/AdguardTeam/AdGuardFilters"
        },
        "Conversion": [
            [
                "Total Lines Processed",
                41199
            ],
            [
                "Comment Lines",
                5724
            ],
            [
                "Empty Lines",
                21
            ],
            [
                "Non-Domain-only Rules Excluded",
                34458
            ],
            [
                "Domain-only Rules Excluded (unsupported options)",
                125
            ],
            [
                "Domain-only Rules Excluded (exception conflict)",
                41
            ],
            [
                "Domain-only Rules Output",
                851
            ]
        ],
        "Output Formats": {
            "Just Domains": "36-justdomains.txt"
        },
        "Domains Output": 851
    },
    {
        "Title": "EasyList ad servers third-party37",
        "Source": "https://raw.githubusercontent.com/AdguardTeam/FiltersRegistry/master/filters/filter_18_Annoyances_Cookies/filter.txt",
        "Base Output Filename": "37-{FORMAT}.txt",
        "Header": {
            "License": "https://github.com/AdguardTeam/AdguardFilters/blob/master/LICENSE",
            "Homepage": "https://github.com/AdguardTeam/AdGuardFilters"
        },
        "Conversion": [
            [
                "Total Lines Processed",
                15339
            ],
            [
                "Comment Lines",
                1838
            ],
            [
                "Empty Lines",
                4
            ],
            [
                "Non-Domain-only Rules Excluded",
                13397
            ],
            [
                "Domain-only Rules Excluded (unsupported options)",
                15
            ],
            [
                "Domain-only Rules Excluded (exception conflict)",
                25
            ],
            [
                "Domain-only Rules Output",
                64
            ]
        ],
        "Output Formats": {
            "Just Domains": "37-justdomains.txt"
        },
        "Domains Output": 64
    },
    {
        "Title": "EasyList ad servers third-party38",
        "Source": "https://raw.githubusercontent.com/AdguardTeam/FiltersRegistry/master/filters/filter_19_Annoyances_Popups/filter.txt",
        "Base Output Filename": "38-{FORMAT}.txt",
        "Header": {
            "License": "https://github.com/AdguardTeam/AdguardFilters/blob/master/LICENSE",
            "Homepage": "https://github.com/AdguardTeam/AdGuardFilters"
        },
        "Conversion": [
            [
                "Total Lines Processed",
                14703
            ],
            [
                "Comment Lines",
                925
            ],
            [
                "Empty Lines",
                11
            ],
            [
                "Non-Domain-only Rules Excluded",
                13156
            ],
            [
                "Domain-only Rules Excluded (unsupported options)",
                36
            ],
            [
                "Domain-only Rules Excluded (exception conflict)",
                13
            ],
            [
                "Domain-only Rules Output",
                573
            ]
        ],
        "Output Formats": {
            "Just Domains": "38-justdomains.txt"
        },
        "Domains Output": 573
    },
    {
        "Title": "EasyList ad servers third-party39",
        "Source": "https://raw.githubusercontent.com/AdguardTeam/FiltersRegistry/master/filters/filter_20_Annoyances_MobileApp/filter.txt",
        "Base Output Filename": "39-{FORMAT}.txt",
        "Header": {
            "License": "https://github.com/AdguardTeam/AdguardFilters/blob/master/LICENSE",
            "Homepage": "https://github.com/AdguardTeam/AdGuardFilters"
        },
        "Conversion": [
            [
                "Total Lines Processed",
                2421
            ],
            [
                "Comment Lines",
                231
            ],
            [
                "Empty Lines",
                4
            ],
            [
                "Non-Domain-only Rules Excluded",
                2187
            ],
            [
                "Domain-only Rules Excluded (unsupported options)",
                1
            ],
            [
                "Domain-only Rules Excluded (exception conflict)",
                0
            ],
            [
                "Domain-only Rules Output",
                2
            ]
        ],
        "Output Formats": {
            "Just Domains": "39-justdomains.txt"
        },
        "Domains Output": 2
    },
    {
        "Title": "EasyList ad servers third-party40",
        "Source": "https://raw.githubusercontent.com/AdguardTeam/FiltersRegistry/master/filters/filter_22_Annoyances_Widgets/filter.txt",
        "Base Output Filename": "40-{FORMAT}.txt",
        "Header": {
            "License": "https://github.com/AdguardTeam/AdguardFilters/blob/master/LICENSE",
            "Homepage": "https://github.com/AdguardTeam/AdGuardFilters"
        },
        "Conversion": [
            [
                "Total Lines Processed",
                1257
            ],
            [
                "Comment Lines",
                236
            ],
            [
                "Empty Lines",
                2
            ],
            [
                "Non-Domain-only Rules Excluded",
                781
            ],
            [
                "Domain-only Rules Excluded (unsupported options)",
                36
            ],
            [
                "Domain-only Rules Excluded (exception conflict)",
                3
            ],
            [
                "Domain-only Rules Output",
                201
            ]
        ],
        "Output Formats": {
            "Just Domains": "40-justdomains.txt"
        },
        "Domains Output": 201
    },
    {
        "Title": "EasyList ad servers third-party41",
        "Source": "https://raw.githubusercontent.com/AdguardTeam/FiltersRegistry/master/filters/filter_21_Annoyances_Other/filter.txt",
        "Base Output Filename": "41-{FORMAT}.txt",
        "Header": {
            "License": "https://github.com/AdguardTeam/AdguardFilters/blob/master/LICENSE",
            "Homepage": "https://github.com/AdguardTeam/AdGuardFilters"
        },
        "Conversion": [
            [
                "Total Lines Processed",
                7758
            ],
            [
                "Comment Lines",
                2725
            ],
            [
                "Empty Lines",
                4
            ],
            [
                "Non-Domain-only Rules Excluded",
                4985
            ],
            [
                "Domain-only Rules Excluded (unsupported options)",
                37
            ],
            [
                "Domain-only Rules Excluded (exception conflict)",
                0
            ],
            [
                "Domain-only Rules Output",
                11
            ]
        ],
        "Output Formats": {
            "Just Domains": "41-justdomains.txt"
        },
        "Domains Output": 11
    },
    {
        "Title": "EasyList ad servers third-party42",
        "Source": "https://raw.githubusercontent.com/AdguardTeam/FiltersRegistry/master/filters/filter_1_Russian/filter.txt",
        "Base Output Filename": "42-{FORMAT}.txt",
        "Header": {
            "License": "https://github.com/AdguardTeam/AdguardFilters/blob/master/LICENSE",
            "Homepage": "https://github.com/AdguardTeam/AdGuardFilters"
        },
        "Conversion": [
            [
                "Total Lines Processed",
                24210
            ],
            [
                "Comment Lines",
                3232
            ],
            [
                "Empty Lines",
                9
            ],
            [
                "Non-Domain-only Rules Excluded",
                16911
            ],
            [
                "Domain-only Rules Excluded (unsupported options)",
                215
            ],
            [
                "Domain-only Rules Excluded (exception conflict)",
                1500
            ],
            [
                "Domain-only Rules Output",
                2352
            ]
        ],
        "Output Formats": {
            "Just Domains": "42-justdomains.txt"
        },
        "Domains Output": 2352
    },
    {
        "Title": "EasyList ad servers third-party43",
        "Source": "https://raw.githubusercontent.com/AdguardTeam/FiltersRegistry/master/filters/filter_6_German/filter.txt",
        "Base Output Filename": "43-{FORMAT}.txt",
        "Header": {
            "License": "https://github.com/AdguardTeam/AdguardFilters/blob/master/LICENSE",
            "Homepage": "https://github.com/AdguardTeam/AdGuardFilters"
        },
        "Conversion": [
            [
                "Total Lines Processed",
                11271
            ],
            [
                "Comment Lines",
                1704
            ],
            [
                "Empty Lines",
                10
            ],
            [
                "Non-Domain-only Rules Excluded",
                9042
            ],
            [
                "Domain-only Rules Excluded (unsupported options)",
                121
            ],
            [
                "Domain-only Rules Excluded (exception conflict)",
                171
            ],
            [
                "Domain-only Rules Output",
                233
            ]
        ],
        "Output Formats": {
            "Just Domains": "43-justdomains.txt"
        },
        "Domains Output": 233
    },
    {
        "Title": "EasyList ad servers third-party45",
        "Source": "https://raw.githubusercontent.com/AdguardTeam/FiltersRegistry/master/filters/filter_7_Japanese/filter.txt",
        "Base Output Filename": "44-{FORMAT}.txt",
        "Header": {
            "License": "https://github.com/AdguardTeam/AdguardFilters/blob/master/LICENSE",
            "Homepage": "https://github.com/AdguardTeam/AdGuardFilters"
        },
        "Conversion": [
            [
                "Total Lines Processed",
                6974
            ],
            [
                "Comment Lines",
                630
            ],
            [
                "Empty Lines",
                7
            ],
            [
                "Non-Domain-only Rules Excluded",
                5967
            ],
            [
                "Domain-only Rules Excluded (unsupported options)",
                44
            ],
            [
                "Domain-only Rules Excluded (exception conflict)",
                17
            ],
            [
                "Domain-only Rules Output",
                316
            ]
        ],
        "Output Formats": {
            "Just Domains": "44-justdomains.txt"
        },
        "Domains Output": 316
    },
    {
        "Title": "EasyList ad servers third-party46",
        "Source": "https://raw.githubusercontent.com/AdguardTeam/FiltersRegistry/master/filters/filter_8_Dutch/filter.txt",
        "Base Output Filename": "45-{FORMAT}.txt",
        "Header": {
            "License": "https://github.com/AdguardTeam/AdguardFilters/blob/master/LICENSE",
            "Homepage": "https://github.com/AdguardTeam/AdGuardFilters"
        },
        "Conversion": [
            [
                "Total Lines Processed",
                1580
            ],
            [
                "Comment Lines",
                248
            ],
            [
                "Empty Lines",
                10
            ],
            [
                "Non-Domain-only Rules Excluded",
                1282
            ],
            [
                "Domain-only Rules Excluded (unsupported options)",
                4
            ],
            [
                "Domain-only Rules Excluded (exception conflict)",
                2
            ],
            [
                "Domain-only Rules Output",
                44
            ]
        ],
        "Output Formats": {
            "Just Domains": "45-justdomains.txt"
        },
        "Domains Output": 44
    },
    {
        "Title": "EasyList ad servers third-party47",
        "Source": "https://raw.githubusercontent.com/AdguardTeam/FiltersRegistry/master/filters/filter_9_Spanish/filter.txt",
        "Base Output Filename": "46-{FORMAT}.txt",
        "Header": {
            "License": "https://github.com/AdguardTeam/AdguardFilters/blob/master/LICENSE",
            "Homepage": "https://github.com/AdguardTeam/AdGuardFilters"
        },
        "Conversion": [
            [
                "Total Lines Processed",
                5435
            ],
            [
                "Comment Lines",
                1128
            ],
            [
                "Empty Lines",
                8
            ],
            [
                "Non-Domain-only Rules Excluded",
                4063
            ],
            [
                "Domain-only Rules Excluded (unsupported options)",
                38
            ],
            [
                "Domain-only Rules Excluded (exception conflict)",
                3
            ],
            [
                "Domain-only Rules Output",
                203
            ]
        ],
        "Output Formats": {
            "Just Domains": "46-justdomains.txt"
        },
        "Domains Output": 203
    },
    {
        "Title": "EasyList ad servers third-party48",
        "Source": "https://raw.githubusercontent.com/AdguardTeam/FiltersRegistry/master/filters/filter_13_Turkish/filter.txt",
        "Base Output Filename": "47-{FORMAT}.txt",
        "Header": {
            "License": "https://github.com/AdguardTeam/AdguardFilters/blob/master/LICENSE",
            "Homepage": "https://github.com/AdguardTeam/AdGuardFilters"
        },
        "Conversion": [
            [
                "Total Lines Processed",
                6506
            ],
            [
                "Comment Lines",
                830
            ],
            [
                "Empty Lines",
                8
            ],
            [
                "Non-Domain-only Rules Excluded",
                5313
            ],
            [
                "Domain-only Rules Excluded (unsupported options)",
                29
            ],
            [
                "Domain-only Rules Excluded (exception conflict)",
                2
            ],
            [
                "Domain-only Rules Output",
                332
            ]
        ],
        "Output Formats": {
            "Just Domains": "47-justdomains.txt"
        },
        "Domains Output": 332
    },
    {
        "Title": "EasyList ad servers third-party49",
        "Source": "https://raw.githubusercontent.com/AdguardTeam/FiltersRegistry/master/filters/filter_224_Chinese/filter.txt",
        "Base Output Filename": "48-{FORMAT}.txt",
        "Header": {
            "License": "https://github.com/AdguardTeam/AdguardFilters/blob/master/LICENSE",
            "Homepage": "https://github.com/AdguardTeam/AdGuardFilters"
        },
        "Conversion": [
            [
                "Total Lines Processed",
                25436
            ],
            [
                "Comment Lines",
                684
            ],
            [
                "Empty Lines",
                7
            ],
            [
                "Non-Domain-only Rules Excluded",
                15048
            ],
            [
                "Domain-only Rules Excluded (unsupported options)",
                233
            ],
            [
                "Domain-only Rules Excluded (exception conflict)",
                18
            ],
            [
                "Domain-only Rules Output",
                9453
            ]
        ],
        "Output Formats": {
            "Just Domains": "48-justdomains.txt"
        },
        "Domains Output": 9453
    },
    {
        "Title": "EasyList ad servers third-party50",
        "Source": "https://raw.githubusercontent.com/AdguardTeam/FiltersRegistry/master/filters/filter_11_Mobile/filter.txt",
        "Base Output Filename": "49-{FORMAT}.txt",
        "Header": {
            "License": "https://github.com/AdguardTeam/AdguardFilters/blob/master/LICENSE",
            "Homepage": "https://github.com/AdguardTeam/AdGuardFilters"
        },
        "Conversion": [
            [
                "Total Lines Processed",
                7003
            ],
            [
                "Comment Lines",
                1068
            ],
            [
                "Empty Lines",
                10
            ],
            [
                "Non-Domain-only Rules Excluded",
                4464
            ],
            [
                "Domain-only Rules Excluded (unsupported options)",
                438
            ],
            [
                "Domain-only Rules Excluded (exception conflict)",
                31
            ],
            [
                "Domain-only Rules Output",
                1002
            ]
        ],
        "Output Formats": {
            "Just Domains": "49-justdomains.txt"
        },
        "Domains Output": 1002
    },
    {
        "Title": "AdGuard Base filter ad servers51",
        "Source": "https://raw.githubusercontent.com/uBlockOrigin/uAssets/master/filters/unbreak.txt",
        "Base Output Filename": "50-{FORMAT}.txt",
        "Header": {
            "Last Modified": "%timestamp%",
            "License": "https://github.com/uBlockOrigin/uAssets/blob/master/LICENSE",
            "Title": "uBlock\u2080 filters \u2013 Unbreak",
            "Homepage": "https://github.com/uBlockOrigin/uAssets"
        },
        "Conversion": [
            [
                "Total Lines Processed",
                4750
            ],
            [
                "Comment Lines",
                1519
            ],
            [
                "Empty Lines",
                1306
            ],
            [
                "Non-Domain-only Rules Excluded",
                3006
            ],
            [
                "Domain-only Rules Excluded (unsupported options)",
                224
            ],
            [
                "Domain-only Rules Excluded (exception conflict)",
                0
            ],
            [
                "Domain-only Rules Output",
                1
            ]
        ],
        "Output Formats": {
            "Just Domains": "50-justdomains.txt"
        },
        "Domains Output": 1
    },
    {
        "Title": "AdGuard Base filter ad servers52",
        "Source": "https://raw.githubusercontent.com/uBlockOrigin/uAssets/master/filters/annoyances.txt",
        "Base Output Filename": "51-{FORMAT}.txt",
        "Header": {
            "Last Modified": "%timestamp%",
            "License": "https://github.com/uBlockOrigin/uAssets/blob/master/LICENSE",
            "Title": "uBlock\u2080 filters \u2013 Annoyances",
            "Homepage": "https://github.com/uBlockOrigin/uAssets"
        },
        "Conversion": [
            [
                "Total Lines Processed",
                6911
            ],
            [
                "Comment Lines",
                1949
            ],
            [
                "Empty Lines",
                1841
            ],
            [
                "Non-Domain-only Rules Excluded",
                4939
            ],
            [
                "Domain-only Rules Excluded (unsupported options)",
                21
            ],
            [
                "Domain-only Rules Excluded (exception conflict)",
                0
            ],
            [
                "Domain-only Rules Output",
                2
            ]
        ],
        "Output Formats": {
            "Just Domains": "51-justdomains.txt"
        },
        "Domains Output": 2
    },
    {
        "Title": "AdGuard Base filter ad servers53",
        "Source": "https://raw.githubusercontent.com/uBlockOrigin/uAssets/master/filters/badware.txt",
        "Base Output Filename": "52-{FORMAT}.txt",
        "Header": {
            "Last Modified": "%timestamp%",
            "License": "https://github.com/uBlockOrigin/uAssets/blob/master/LICENSE",
            "Title": "uBlock\u2080 filters \u2013 Badware risks",
            "Homepage": "https://github.com/uBlockOrigin/uAssets"
        },
        "Conversion": [
            [
                "Total Lines Processed",
                1450
            ],
            [
                "Comment Lines",
                247
            ],
            [
                "Empty Lines",
                146
            ],
            [
                "Non-Domain-only Rules Excluded",
                323
            ],
            [
                "Domain-only Rules Excluded (unsupported options)",
                796
            ],
            [
                "Domain-only Rules Excluded (exception conflict)",
                0
            ],
            [
                "Domain-only Rules Output",
                84
            ]
        ],
        "Output Formats": {
            "Just Domains": "52-justdomains.txt"
        },
        "Domains Output": 84
    },
    {
        "Title": "AdGuard Base filter ad servers54",
        "Source": "https://raw.githubusercontent.com/uBlockOrigin/uAssets/master/filters/legacy.txt",
        "Base Output Filename": "53-{FORMAT}.txt",
        "Header": {
            "Last Modified": "%timestamp%",
            "License": "https://github.com/uBlockOrigin/uAssets/blob/master/LICENSE",
            "Title": "uBlock\u2080 filters -- Legacy",
            "Homepage": "https://github.com/uBlockOrigin/uAssets"
        },
        "Conversion": [
            [
                "Total Lines Processed",
                152
            ],
            [
                "Comment Lines",
                49
            ],
            [
                "Empty Lines",
                22
            ],
            [
                "Non-Domain-only Rules Excluded",
                95
            ],
            [
                "Domain-only Rules Excluded (unsupported options)",
                8
            ],
            [
                "Domain-only Rules Excluded (exception conflict)",
                0
            ],
            [
                "Domain-only Rules Output",
                0
            ]
        ],
        "Output Formats": {
            "Just Domains": "53-justdomains.txt"
        },
        "Domains Output": 0
    },
    {
        "Title": "AdGuard Base filter ad servers55",
        "Source": "https://raw.githubusercontent.com/uBlockOrigin/uAssets/master/filters/privacy.txt",
        "Base Output Filename": "54-{FORMAT}.txt",
        "Header": {
            "Last Modified": "%timestamp%",
            "License": "https://github.com/uBlockOrigin/uAssets/blob/master/LICENSE",
            "Title": "uBlock\u2080 filters \u2013 Privacy",
            "Homepage": "https://github.com/uBlockOrigin/uAssets"
        },
        "Conversion": [
            [
                "Total Lines Processed",
                429
            ],
            [
                "Comment Lines",
                149
            ],
            [
                "Empty Lines",
                101
            ],
            [
                "Non-Domain-only Rules Excluded",
                234
            ],
            [
                "Domain-only Rules Excluded (unsupported options)",
                14
            ],
            [
                "Domain-only Rules Excluded (exception conflict)",
                0
            ],
            [
                "Domain-only Rules Output",
                32
            ]
        ],
        "Output Formats": {
            "Just Domains": "54-justdomains.txt"
        },
        "Domains Output": 32
    },
    {
        "Title": "AdGuard Base filter ad servers56",
        "Source": "https://raw.githubusercontent.com/uBlockOrigin/uAssets/master/filters/resource-abuse.txt",
        "Base Output Filename": "55-{FORMAT}.txt",
        "Header": {
            "Last Modified": "%timestamp%",
            "License": "https://github.com/uBlockOrigin/uAssets/blob/master/LICENSE",
            "Title": "uBlock\u2080 filters \u2013 Resource abuse",
            "Homepage": "https://github.com/uBlockOrigin/uAssets"
        },
        "Conversion": [
            [
                "Total Lines Processed",
                145
            ],
            [
                "Comment Lines",
                53
            ],
            [
                "Empty Lines",
                40
            ],
            [
                "Non-Domain-only Rules Excluded",
                75
            ],
            [
                "Domain-only Rules Excluded (unsupported options)",
                14
            ],
            [
                "Domain-only Rules Excluded (exception conflict)",
                0
            ],
            [
                "Domain-only Rules Output",
                3
            ]
        ],
        "Output Formats": {
            "Just Domains": "55-justdomains.txt"
        },
        "Domains Output": 3
    },
    {
        "Title": "AdGuard Base filter ad servers57",
        "Source": "https://raw.githubusercontent.com/uBlockOrigin/uAssets/master/filters/filters.txt",
        "Base Output Filename": "56-{FORMAT}.txt",
        "Header": {
            "Last Modified": "%timestamp%",
            "License": "https://github.com/uBlockOrigin/uAssets/blob/master/LICENSE",
            "Title": "uBlock\u2080 filters",
            "Homepage": "https://github.com/uBlockOrigin/uAssets"
        },
        "Conversion": [
            [
                "Total Lines Processed",
                19611
            ],
            [
                "Comment Lines",
                4481
            ],
            [
                "Empty Lines",
                3612
            ],
            [
                "Non-Domain-only Rules Excluded",
                14544
            ],
            [
                "Domain-only Rules Excluded (unsupported options)",
                404
            ],
            [
                "Domain-only Rules Excluded (exception conflict)",
                0
            ],
            [
                "Domain-only Rules Output",
                182
            ]
        ],
        "Output Formats": {
            "Just Domains": "56-justdomains.txt"
        },
        "Domains Output": 182
    },
    {
        "Title": "AdGuard Base filter ad servers61",
        "Source": "https://raw.githubusercontent.com/AdguardTeam/AdguardFilters/master/BaseFilter/sections/adservers.txt",
        "Base Output Filename": "60-{FORMAT}.txt",
        "Header": {},
        "Conversion": [
            [
                "Total Lines Processed",
                1364
            ],
            [
                "Comment Lines",
                33
            ],
            [
                "Empty Lines",
                1
            ],
            [
                "Non-Domain-only Rules Excluded",
                23
            ],
            [
                "Domain-only Rules Excluded (unsupported options)",
                259
            ],
            [
                "Domain-only Rules Excluded (exception conflict)",
                1
            ],
            [
                "Domain-only Rules Output",
                1048
            ]
        ],
        "Output Formats": {
            "Just Domains": "60-justdomains.txt"
        },
        "Domains Output": 1048
    },
    {
        "Title": "AdGuard Base filter ad servers62",
        "Source": "https://raw.githubusercontent.com/AdguardTeam/AdguardFilters/master/BaseFilter/sections/cryptominers.txt",
        "Base Output Filename": "61-{FORMAT}.txt",
        "Header": {},
        "Conversion": [
            [
                "Total Lines Processed",
                244
            ],
            [
                "Comment Lines",
                29
            ],
            [
                "Empty Lines",
                1
            ],
            [
                "Non-Domain-only Rules Excluded",
                88
            ],
            [
                "Domain-only Rules Excluded (unsupported options)",
                4
            ],
            [
                "Domain-only Rules Excluded (exception conflict)",
                0
            ],
            [
                "Domain-only Rules Output",
                123
            ]
        ],
        "Output Formats": {
            "Just Domains": "61-justdomains.txt"
        },
        "Domains Output": 123
    }
]